Metadata-Version: 2.1
Name: repometrics
Version: 0.0.2
Summary: CLI to display current repository files path and languages.
Home-page: https://github.com/alextxj/RepoMetrics
Author: Alex Tian Xing Jian
Author-email: tian.xingjian@hotmail.com
License: MIT
Platform: UNKNOWN
Classifier: Programming Language :: Python :: 3
Classifier: License :: OSI Approved :: MIT License
Classifier: Operating System :: OS Independent
Requires-Python: >=3.6
License-File: LICENSE
